{
  "created_utc": "2026-05-06T14:46:39.181070+00:00",
  "source_snapshot_tar": {
    "name": "class_a10_2f_snapshot_20260506_234458.tar.gz",
    "sha256": "647fb39d12f9dec21235fa573d338f96af2f76242f01908e78286436ca968132",
    "size_bytes": 2118844
  },
  "snapshot_file_count": 237,
  "snapshot_total_size_bytes": 7881366,
  "worktree_total_size_reported": "2.6G",
  "upstream_or_worktree_HEAD": "e85808324f51fc694d12e3ed7439552a3c3f9540",
  "git_log_1": "e8580832 (HEAD -> master, tag: v3.3.4, origin/master, origin/HEAD) Fixed shoorting bug (negative dx); store Omega_m(z) and Omega_r(z) in background table.",
  "git_remote": "origin\thttps://github.com/lesgourg/class_public.git (fetch)\norigin\thttps://github.com/lesgourg/class_public.git (push)",
  "git_status_short_preview": " M include/background.h\n M include/perturbations.h\n D output/explanatory00_cl.dat\n D output/explanatory00_cl_lensed.dat\n D output/explanatory00_pk.dat\n M source/background.c\n M source/input.c\n M source/perturbations.c\n?? 137_gate_evolution.png\n?? The_Final_Universe.png\n?? The_Final_Universe.py\n?? _classy.cpython-312-x86_64-linux-gnu.so\n?? a10_2f_ef.input.yaml\n?? a10_2f_ef.input.yaml.locked\n?? a10_2f_ef.updated.yaml\n?? a10_2f_ef.yaml\n?? a10_2f_ef_safe.yaml\n?? a10_bao_run.1.txt\n?? a10_bao_run.checkpoint\n?? a10_bao_run.converge\n?? a10_bao_run.corr\n?? a10_bao_run.covmat\n?? a10_bao_run.input.yaml\n?? a10_bao_run.input.yaml.locked\n?? a10_bao_run.likestats\n?? a10_bao_run.log\n?? a10_bao_run.margestats\n?? a10_bao_run.progress\n?? a10_bao_run.updated.yaml\n?? a10_bao_test.input.yaml\n?? a10_debug.yaml\n?? a10_env/\n?? a10_main_rescue.converge\n?? a10_main_rescue.corr\n?? a10_main_rescue.covmat\n?? a10_main_rescue.likestats\n?? a10_main_rescue.log\n?? a10_main_rescue.log.BAK\n?? a10_main_rescue.margestats\n?? a10_main_rescue.yaml\n?? a10_phase4_shoes.yaml\n?? a10_prod_run.2.txt.bak\n?? a10_prod_run.converge\n?? a10_prod_run.corr\n?? a10_prod_run.covmat\n?? a10_prod_run.likestats\n?? a10_prod_run.margestats\n?? a10_production.yaml\n?? a10_profile_68.yaml\n?? a10_profile_69.yaml\n?? a10_profile_70.yaml\n?? a10_profile_71.yaml\n?? a10_profile_72.yaml\n?? a10_profile_73.yaml\n?? a10_rescue.yaml\n?? a10_safe_plot.png\n?? a10_scout_H0_72.yaml\n?? a10_single_victory.png\n?? a10_test_00_background.dat\n?? a10_test_00_cl.dat\n?? a10_test_00_pk.dat\n?? a10_test_00_tk.dat\n?? a10_triangle_plot.png\n?? a10_wp0.yaml\n?? a10_wp0_valley.converge\n?? a10_wp0_valley.corr\n?? a10_wp0_valley.covmat\n?? a10_wp0_valley.likestats\n?? a10_wp0_valley.margestats\n?? all_code.txt\n?? analyze_gate.py\n?? analyze_matter.py\n?? auto_fix.py\n?? auto_test_a10.py\n?? build_error.log\n?? chains/\n?? check_73.py\n?? classy.egg-info/\n?? cmb_comparison.png\n?? cmb_spectrum_a10.png\n?? cmb_validation_golden_model.py\n?? cobaya_packages/\n?? compare_cmb.py\n?? daf\n?? debug_a10_point.py\n?? diagnostic_final_ignition.png\n?? diagnostic_rs_ignition.png\n?? diagnostic_rs_single.png\n?? diagnostic_true_mountain.png\n?? final_audit.py\n?? fix_class_args.py\n?? fix_segfault_a10.py\n?? fix_yaml.py\n?? free_a10_parser.py\n?? full_debug_log.txt\n?? generate_a10_only.py\n?? get_bestfit.py\n?? hybrid_a10_tx_run.1.txt\n?? hybrid_a10_tx_run.checkpoint\n?? hybrid_a10_tx_run.covmat\n?? hybrid_a10_tx_run.input.yaml\n?? hybrid_a10_tx_run.progress\n?? hybrid_a10_tx_run.updated.yaml\n?? hybrid_spectra_comparison.png\n?? hybrid_v2.yaml\n?? include/background.h.a10_bak\n?? lcdm_data.npz\n?? matter_analysis.png\n?? my_old_classy_script.py\n?? packages/\n?? plot_a10.py\n?? plot_background.py\n?? plot_cmb.py\n?? plot_hybrid_spectra.py\n?? python/classy.egg-info/\n?? remove_drop.py\n?? rescue_a10.py\n?? residual_plot.png\n?? rs_evolution.png\n?? run_a10_final.py\n?? run_a10_h0_free.py\n?? run_a10_success.py\n?? run_ratio_test.py\n?? sanity_check.png\n?? scan_jacobian.py\n?? scan_residual.py\n?? scientific_analysis.png\n?? step1_lcdm.py\n?? step2_a10_ratio.py\n?? test_H0_70.19.png\n?? test_H0_72.69.png\n?? test_H0_73.26.png\n?? test_H0_73.83.png\n?? test_H0_74.47.png\n?? test_H0_75.94.png\n?? test_a10.py\n?? test_a10_evaluation.py\n?? test_a10_final.py\n?? test_hybrid_collision.py\n?? test_isolate.py\n?? test_lcdm.py\n?? test_perturbations.py\n?? the_ratio_test.png\n?? unified_a10.yaml\n?? verify_residual.py\n",
  "local_diff_info": [
    {
      "path": "legacy_class_worktrees/class_a10_2f_snapshot_20260506_234458/class_a10_2f_local_diff.patch",
      "size_bytes": 1079651,
      "contains_a10_keywords": true,
      "diff_file_count": 8,
      "diff_files_preview": [
        {
          "a": "include/background.h",
          "b": "include/background.h"
        },
        {
          "a": "include/perturbations.h",
          "b": "include/perturbations.h"
        },
        {
          "a": "output/explanatory00_cl.dat",
          "b": "output/explanatory00_cl.dat"
        },
        {
          "a": "output/explanatory00_cl_lensed.dat",
          "b": "output/explanatory00_cl_lensed.dat"
        },
        {
          "a": "output/explanatory00_pk.dat",
          "b": "output/explanatory00_pk.dat"
        },
        {
          "a": "source/background.c",
          "b": "source/background.c"
        },
        {
          "a": "source/input.c",
          "b": "source/input.c"
        },
        {
          "a": "source/perturbations.c",
          "b": "source/perturbations.c"
        }
      ]
    }
  ],
  "large_git_artifacts_preview": [
    {
      "size_bytes": 841981679,
      "path": "/home/kei/class_a10_2f/.git/objects/pack/pack-5e49e2e09b8ef64a0e788582c6a0cf52cd9aaa32.pack"
    },
    {
      "size_bytes": 878508,
      "path": "/home/kei/class_a10_2f/.git/objects/pack/pack-5e49e2e09b8ef64a0e788582c6a0cf52cd9aaa32.idx"
    },
    {
      "size_bytes": 125400,
      "path": "/home/kei/class_a10_2f/.git/objects/pack/pack-5e49e2e09b8ef64a0e788582c6a0cf52cd9aaa32.rev"
    }
  ],
  "large_chain_outputs_preview": [
    {
      "size_bytes": 112233041,
      "path": "/home/kei/class_a10_2f/chains/a10_run2.1.txt"
    },
    {
      "size_bytes": 60331967,
      "path": "/home/kei/class_a10_2f/packages/data/bao_data/sdss_DR16_ELG_FSBAO_DMDHfs8gridlikelihood.txt"
    },
    {
      "size_bytes": 60331967,
      "path": "/home/kei/class_a10_2f/cobaya_packages/data/bao_data/sdss_DR16_ELG_FSBAO_DMDHfs8gridlikelihood.txt"
    },
    {
      "size_bytes": 54780270,
      "path": "/home/kei/class_a10_2f/chains/a10_main_rescue.1.txt"
    },
    {
      "size_bytes": 53523861,
      "path": "/home/kei/class_a10_2f/packages/data/sn_data/DESY5/covsys_000.txt"
    },
    {
      "size_bytes": 53523861,
      "path": "/home/kei/class_a10_2f/cobaya_packages/data/sn_data/DESY5/covsys_000.txt"
    },
    {
      "size_bytes": 44646405,
      "path": "/home/kei/class_a10_2f/chains/a10_wp0_valley.1.txt"
    },
    {
      "size_bytes": 12087118,
      "path": "/home/kei/class_a10_2f/packages/data/sn_data/Pantheon/sys_full_long.txt"
    },
    {
      "size_bytes": 12087118,
      "path": "/home/kei/class_a10_2f/cobaya_packages/data/sn_data/Pantheon/sys_full_long.txt"
    },
    {
      "size_bytes": 7282780,
      "path": "/home/kei/class_a10_2f/chains/a10_phase4_shoes.1.txt"
    },
    {
      "size_bytes": 6341136,
      "path": "/home/kei/class_a10_2f/packages/data/planck_2018_lowT_native/cl2x_2.txt"
    },
    {
      "size_bytes": 6341136,
      "path": "/home/kei/class_a10_2f/cobaya_packages/data/planck_2018_lowT_native/cl2x_2.txt"
    },
    {
      "size_bytes": 6225000,
      "path": "/home/kei/class_a10_2f/packages/data/planck_2018_lowT_native/cl2x_1.txt"
    },
    {
      "size_bytes": 6225000,
      "path": "/home/kei/class_a10_2f/cobaya_packages/data/planck_2018_lowT_native/cl2x_1.txt"
    },
    {
      "size_bytes": 4498416,
      "path": "/home/kei/class_a10_2f/a10_bao_run.1.txt"
    },
    {
      "size_bytes": 2187000,
      "path": "/home/kei/class_a10_2f/packages/data/planck_2018_lowE_native/prob_table.txt"
    },
    {
      "size_bytes": 2187000,
      "path": "/home/kei/class_a10_2f/cobaya_packages/data/planck_2018_lowE_native/prob_table.txt"
    },
    {
      "size_bytes": 1582091,
      "path": "/home/kei/class_a10_2f/packages/data/planck_2018_lowT_native/cov.txt"
    },
    {
      "size_bytes": 1582091,
      "path": "/home/kei/class_a10_2f/cobaya_packages/data/planck_2018_lowT_native/cov.txt"
    },
    {
      "size_bytes": 1432417,
      "path": "/home/kei/class_a10_2f/chains/a10_run1.1.txt"
    },
    {
      "size_bytes": 926598,
      "path": "/home/kei/class_a10_2f/a10_prod_run.2.txt.bak"
    },
    {
      "size_bytes": 911816,
      "path": "/home/kei/class_a10_2f/chains/a10_prod_run.5.txt"
    },
    {
      "size_bytes": 867470,
      "path": "/home/kei/class_a10_2f/chains/a10_prod_run.4.txt"
    },
    {
      "size_bytes": 831682,
      "path": "/home/kei/class_a10_2f/chains/a10_prod_run.3.txt"
    },
    {
      "size_bytes": 822346,
      "path": "/home/kei/class_a10_2f/chains/a10_prod_run.1.txt"
    },
    {
      "size_bytes": 434070,
      "path": "/home/kei/class_a10_2f/chains/a10_scout_H0_72.1.txt"
    },
    {
      "size_bytes": 187568,
      "path": "/home/kei/class_a10_2f/packages/data/bao_data/sdss_DR16_LYxQSO_BAO_DMDHgrid.txt"
    },
    {
      "size_bytes": 187568,
      "path": "/home/kei/class_a10_2f/cobaya_packages/data/bao_data/sdss_DR16_LYxQSO_BAO_DMDHgrid.txt"
    },
    {
      "size_bytes": 187499,
      "path": "/home/kei/class_a10_2f/packages/data/bao_data/sdss_DR16_LYAUTO_BAO_DMDHgrid.txt"
    },
    {
      "size_bytes": 187499,
      "path": "/home/kei/class_a10_2f/cobaya_packages/data/bao_data/sdss_DR16_LYAUTO_BAO_DMDHgrid.txt"
    },
    {
      "size_bytes": 104228,
      "path": "/home/kei/class_a10_2f/all_code.txt"
    },
    {
      "size_bytes": 103618,
      "path": "/home/kei/class_a10_2f/packages/data/sn_data/JLA/jla_lcparams.txt"
    },
    {
      "size_bytes": 103618,
      "path": "/home/kei/class_a10_2f/cobaya_packages/data/sn_data/JLA/jla_lcparams.txt"
    }
  ],
  "large_data_likelihood_preview": [
    {
      "size_bytes": 60331967,
      "path": "/home/kei/class_a10_2f/packages/data/bao_data/sdss_DR16_ELG_FSBAO_DMDHfs8gridlikelihood.txt"
    },
    {
      "size_bytes": 60331967,
      "path": "/home/kei/class_a10_2f/cobaya_packages/data/bao_data/sdss_DR16_ELG_FSBAO_DMDHfs8gridlikelihood.txt"
    },
    {
      "size_bytes": 53523861,
      "path": "/home/kei/class_a10_2f/packages/data/sn_data/DESY5/covsys_000.txt"
    },
    {
      "size_bytes": 53523861,
      "path": "/home/kei/class_a10_2f/cobaya_packages/data/sn_data/DESY5/covsys_000.txt"
    },
    {
      "size_bytes": 41921280,
      "path": "/home/kei/class_a10_2f/packages/data/planck_2018/baseline/plc_3.0/hi_l/plik/plik_rd12_HM_v22b_TTTEEE.clik/clik/lkl_0/criterion_gauss_mat"
    },
    {
      "size_bytes": 41921280,
      "path": "/home/kei/class_a10_2f/cobaya_packages/data/planck_2018/baseline/plc_3.0/hi_l/plik/plik_rd12_HM_v22b_TTTEEE.clik/clik/lkl_0/criterion_gauss_mat"
    },
    {
      "size_bytes": 33284960,
      "path": "/home/kei/class_a10_2f/packages/data/sn_data/PantheonPlus/Pantheon+SH0ES_STAT+SYS.cov"
    },
    {
      "size_bytes": 33284960,
      "path": "/home/kei/class_a10_2f/cobaya_packages/data/sn_data/PantheonPlus/Pantheon+SH0ES_STAT+SYS.cov"
    },
    {
      "size_bytes": 12087118,
      "path": "/home/kei/class_a10_2f/packages/data/sn_data/Pantheon/sys_full_long.txt"
    },
    {
      "size_bytes": 12087118,
      "path": "/home/kei/class_a10_2f/cobaya_packages/data/sn_data/Pantheon/sys_full_long.txt"
    },
    {
      "size_bytes": 10088988,
      "path": "/home/kei/class_a10_2f/packages/data/sn_data/JLA/jla_vab_covmatrix.dat"
    },
    {
      "size_bytes": 10088988,
      "path": "/home/kei/class_a10_2f/cobaya_packages/data/sn_data/JLA/jla_vab_covmatrix.dat"
    },
    {
      "size_bytes": 10031226,
      "path": "/home/kei/class_a10_2f/packages/data/sn_data/JLA/jla_v0a_covmatrix.dat"
    },
    {
      "size_bytes": 10031226,
      "path": "/home/kei/class_a10_2f/cobaya_packages/data/sn_data/JLA/jla_v0a_covmatrix.dat"
    },
    {
      "size_bytes": 9980965,
      "path": "/home/kei/class_a10_2f/packages/data/sn_data/JLA/jla_va_covmatrix.dat"
    },
    {
      "size_bytes": 9980965,
      "path": "/home/kei/class_a10_2f/cobaya_packages/data/sn_data/JLA/jla_va_covmatrix.dat"
    },
    {
      "size_bytes": 9858802,
      "path": "/home/kei/class_a10_2f/packages/data/sn_data/JLA/jla_vb_covmatrix.dat"
    },
    {
      "size_bytes": 9858802,
      "path": "/home/kei/class_a10_2f/cobaya_packages/data/sn_data/JLA/jla_vb_covmatrix.dat"
    },
    {
      "size_bytes": 9799920,
      "path": "/home/kei/class_a10_2f/packages/data/sn_data/JLA/jla_v0b_covmatrix.dat"
    },
    {
      "size_bytes": 9799920,
      "path": "/home/kei/class_a10_2f/cobaya_packages/data/sn_data/JLA/jla_v0b_covmatrix.dat"
    },
    {
      "size_bytes": 9549877,
      "path": "/home/kei/class_a10_2f/packages/data/sn_data/JLA/jla_v0_covmatrix.dat"
    },
    {
      "size_bytes": 9549877,
      "path": "/home/kei/class_a10_2f/cobaya_packages/data/sn_data/JLA/jla_v0_covmatrix.dat"
    },
    {
      "size_bytes": 6491520,
      "path": "/home/kei/class_a10_2f/packages/data/planck_2018/baseline/plc_3.0/low_l/commander/commander_dx12_v3_2_29.clik/clik/lkl_0/_external/sigma.fits"
    },
    {
      "size_bytes": 6491520,
      "path": "/home/kei/class_a10_2f/cobaya_packages/data/planck_2018/baseline/plc_3.0/low_l/commander/commander_dx12_v3_2_29.clik/clik/lkl_0/_external/sigma.fits"
    },
    {
      "size_bytes": 6341136,
      "path": "/home/kei/class_a10_2f/packages/data/planck_2018_lowT_native/cl2x_2.txt"
    },
    {
      "size_bytes": 6341136,
      "path": "/home/kei/class_a10_2f/cobaya_packages/data/planck_2018_lowT_native/cl2x_2.txt"
    },
    {
      "size_bytes": 6244951,
      "path": "/home/kei/class_a10_2f/packages/data/sn_data/DES-Dovekie/covtot_inv_000.npz"
    },
    {
      "size_bytes": 6244951,
      "path": "/home/kei/class_a10_2f/cobaya_packages/data/sn_data/DES-Dovekie/covtot_inv_000.npz"
    },
    {
      "size_bytes": 6225000,
      "path": "/home/kei/class_a10_2f/packages/data/planck_2018_lowT_native/cl2x_1.txt"
    },
    {
      "size_bytes": 6225000,
      "path": "/home/kei/class_a10_2f/cobaya_packages/data/planck_2018_lowT_native/cl2x_1.txt"
    },
    {
      "size_bytes": 4685760,
      "path": "/home/kei/class_a10_2f/packages/data/planck_2018/baseline/plc_3.0/hi_l/plik/plik_rd12_HM_v22_TT.clik/clik/lkl_0/criterion_gauss_mat"
    },
    {
      "size_bytes": 4685760,
      "path": "/home/kei/class_a10_2f/cobaya_packages/data/planck_2018/baseline/plc_3.0/hi_l/plik/plik_rd12_HM_v22_TT.clik/clik/lkl_0/criterion_gauss_mat"
    },
    {
      "size_bytes": 4498416,
      "path": "/home/kei/class_a10_2f/a10_bao_run.1.txt"
    },
    {
      "size_bytes": 3461760,
      "path": "/home/kei/class_a10_2f/packages/data/planck_2018/baseline/plc_3.0/hi_l/plik/plik_rd12_HM_v22b_TTTEEE.clik/clik/lkl_0/component_9/template"
    },
    {
      "size_bytes": 3461760,
      "path": "/home/kei/class_a10_2f/packages/data/planck_2018/baseline/plc_3.0/hi_l/plik/plik_rd12_HM_v22b_TTTEEE.clik/clik/lkl_0/component_6/template"
    },
    {
      "size_bytes": 3461760,
      "path": "/home/kei/class_a10_2f/packages/data/planck_2018/baseline/plc_3.0/hi_l/plik/plik_rd12_HM_v22b_TTTEEE.clik/clik/lkl_0/component_11/template"
    },
    {
      "size_bytes": 3461760,
      "path": "/home/kei/class_a10_2f/packages/data/planck_2018/baseline/plc_3.0/hi_l/plik/plik_rd12_HM_v22b_TTTEEE.clik/clik/lkl_0/component_10/template"
    },
    {
      "size_bytes": 3461760,
      "path": "/home/kei/class_a10_2f/packages/data/planck_2018/baseline/plc_3.0/hi_l/plik/plik_rd12_HM_v22_TT.clik/clik/lkl_0/component_8/template"
    },
    {
      "size_bytes": 3461760,
      "path": "/home/kei/class_a10_2f/packages/data/planck_2018/baseline/plc_3.0/hi_l/plik/plik_rd12_HM_v22_TT.clik/clik/lkl_0/component_7/template"
    },
    {
      "size_bytes": 3461760,
      "path": "/home/kei/class_a10_2f/packages/data/planck_2018/baseline/plc_3.0/hi_l/plik/plik_rd12_HM_v22_TT.clik/clik/lkl_0/component_6/template"
    },
    {
      "size_bytes": 3461760,
      "path": "/home/kei/class_a10_2f/cobaya_packages/data/planck_2018/baseline/plc_3.0/hi_l/plik/plik_rd12_HM_v22b_TTTEEE.clik/clik/lkl_0/component_9/template"
    },
    {
      "size_bytes": 3461760,
      "path": "/home/kei/class_a10_2f/cobaya_packages/data/planck_2018/baseline/plc_3.0/hi_l/plik/plik_rd12_HM_v22b_TTTEEE.clik/clik/lkl_0/component_6/template"
    },
    {
      "size_bytes": 3461760,
      "path": "/home/kei/class_a10_2f/cobaya_packages/data/planck_2018/baseline/plc_3.0/hi_l/plik/plik_rd12_HM_v22b_TTTEEE.clik/clik/lkl_0/component_11/template"
    },
    {
      "size_bytes": 3461760,
      "path": "/home/kei/class_a10_2f/cobaya_packages/data/planck_2018/baseline/plc_3.0/hi_l/plik/plik_rd12_HM_v22b_TTTEEE.clik/clik/lkl_0/component_10/template"
    },
    {
      "size_bytes": 3461760,
      "path": "/home/kei/class_a10_2f/cobaya_packages/data/planck_2018/baseline/plc_3.0/hi_l/plik/plik_rd12_HM_v22_TT.clik/clik/lkl_0/component_8/template"
    },
    {
      "size_bytes": 3461760,
      "path": "/home/kei/class_a10_2f/cobaya_packages/data/planck_2018/baseline/plc_3.0/hi_l/plik/plik_rd12_HM_v22_TT.clik/clik/lkl_0/component_7/template"
    },
    {
      "size_bytes": 3461760,
      "path": "/home/kei/class_a10_2f/cobaya_packages/data/planck_2018/baseline/plc_3.0/hi_l/plik/plik_rd12_HM_v22_TT.clik/clik/lkl_0/component_6/template"
    },
    {
      "size_bytes": 3006160,
      "path": "/home/kei/class_a10_2f/packages/data/planck_2018/baseline/plc_3.0/hi_l/plik_lite/plik_lite_v22_TTTEEE.clik/clik/lkl_0/_external/c_matrix_plik_v22.dat"
    },
    {
      "size_bytes": 3006160,
      "path": "/home/kei/class_a10_2f/packages/data/planck_2018/baseline/plc_3.0/hi_l/plik_lite/plik_lite_v22_TT.clik/clik/lkl_0/_external/c_matrix_plik_v22.dat"
    },
    {
      "size_bytes": 3006160,
      "path": "/home/kei/class_a10_2f/cobaya_packages/data/planck_2018/baseline/plc_3.0/hi_l/plik_lite/plik_lite_v22_TTTEEE.clik/clik/lkl_0/_external/c_matrix_plik_v22.dat"
    }
  ],
  "large_build_artifacts_preview": [
    {
      "size_bytes": 21172730,
      "path": "/home/kei/class_a10_2f/cobaya_packages/code/classy/libclass.a"
    },
    {
      "size_bytes": 21172594,
      "path": "/home/kei/class_a10_2f/packages/code/classy_old/libclass.a"
    },
    {
      "size_bytes": 15475096,
      "path": "/home/kei/class_a10_2f/build/lib.linux-x86_64-cpython-312/classy/_classy.cpython-312-x86_64-linux-gnu.so"
    },
    {
      "size_bytes": 15452688,
      "path": "/home/kei/class_a10_2f/a10_env/lib/python3.12/site-packages/classy/_classy.cpython-312-x86_64-linux-gnu.so"
    },
    {
      "size_bytes": 15452360,
      "path": "/home/kei/class_a10_2f/_classy.cpython-312-x86_64-linux-gnu.so"
    },
    {
      "size_bytes": 15435424,
      "path": "/home/kei/class_a10_2f/cobaya_packages/code/classy/build/lib.linux-x86_64-cpython-312/classy/_classy.cpython-312-x86_64-linux-gnu.so"
    },
    {
      "size_bytes": 15435416,
      "path": "/home/kei/class_a10_2f/packages/code/classy_old/build/lib.linux-x86_64-cpython-312/classy/_classy.cpython-312-x86_64-linux-gnu.so"
    },
    {
      "size_bytes": 11689930,
      "path": "/home/kei/class_a10_2f/packages/code/classy_old/external/distortions/Greens_data.dat"
    },
    {
      "size_bytes": 11689930,
      "path": "/home/kei/class_a10_2f/packages/code/classy_old/build/lib.linux-x86_64-cpython-312/classy/external/distortions/Greens_data.dat"
    },
    {
      "size_bytes": 11689930,
      "path": "/home/kei/class_a10_2f/cobaya_packages/code/classy/external/distortions/Greens_data.dat"
    },
    {
      "size_bytes": 11689930,
      "path": "/home/kei/class_a10_2f/cobaya_packages/code/classy/build/lib.linux-x86_64-cpython-312/classy/external/distortions/Greens_data.dat"
    },
    {
      "size_bytes": 11689930,
      "path": "/home/kei/class_a10_2f/build/lib.linux-x86_64-cpython-312/classy/external/distortions/Greens_data.dat"
    },
    {
      "size_bytes": 11689930,
      "path": "/home/kei/class_a10_2f/a10_env/lib/python3.12/site-packages/classy/external/distortions/Greens_data.dat"
    },
    {
      "size_bytes": 10865056,
      "path": "/home/kei/class_a10_2f/cobaya_packages/code/classy/build/temp.linux-x86_64-cpython-312/python/classy.o"
    },
    {
      "size_bytes": 10865048,
      "path": "/home/kei/class_a10_2f/packages/code/classy_old/build/temp.linux-x86_64-cpython-312/python/classy.o"
    },
    {
      "size_bytes": 10858792,
      "path": "/home/kei/class_a10_2f/build/temp.linux-x86_64-cpython-312/python/classy.o"
    },
    {
      "size_bytes": 5197080,
      "path": "/home/kei/class_a10_2f/build/lensing.opp"
    },
    {
      "size_bytes": 5197024,
      "path": "/home/kei/class_a10_2f/packages/code/classy_old/build/lensing.opp"
    },
    {
      "size_bytes": 5197024,
      "path": "/home/kei/class_a10_2f/cobaya_packages/code/classy/build/lensing.opp"
    },
    {
      "size_bytes": 4441704,
      "path": "/home/kei/class_a10_2f/a10_env/lib/python3.12/site-packages/astropy/wcs/_wcs.abi3.so"
    },
    {
      "size_bytes": 3991252,
      "path": "/home/kei/class_a10_2f/python/classy.cpp"
    },
    {
      "size_bytes": 3991252,
      "path": "/home/kei/class_a10_2f/build/lib.linux-x86_64-cpython-312/classy/python/classy.cpp"
    },
    {
      "size_bytes": 3990370,
      "path": "/home/kei/class_a10_2f/a10_env/lib/python3.12/site-packages/classy/python/classy.cpp"
    },
    {
      "size_bytes": 3964103,
      "path": "/home/kei/class_a10_2f/cobaya_packages/code/classy/python/classy.cpp"
    },
    {
      "size_bytes": 3964091,
      "path": "/home/kei/class_a10_2f/packages/code/classy_old/python/classy.cpp"
    },
    {
      "size_bytes": 2565256,
      "path": "/home/kei/class_a10_2f/a10_env/lib/python3.12/site-packages/astropy/io/ascii/cparser.abi3.so"
    },
    {
      "size_bytes": 2405408,
      "path": "/home/kei/class_a10_2f/build/perturbations.opp"
    },
    {
      "size_bytes": 2402128,
      "path": "/home/kei/class_a10_2f/cobaya_packages/code/classy/build/perturbations.opp"
    },
    {
      "size_bytes": 2402120,
      "path": "/home/kei/class_a10_2f/packages/code/classy_old/build/perturbations.opp"
    },
    {
      "size_bytes": 2195808,
      "path": "/home/kei/class_a10_2f/a10_env/lib/python3.12/site-packages/mpi4py/MPI.openmpi.cpython-312-x86_64-linux-gnu.so"
    },
    {
      "size_bytes": 2183648,
      "path": "/home/kei/class_a10_2f/a10_env/lib/python3.12/site-packages/mpi4py/MPI.mpich.cpython-312-x86_64-linux-gnu.so"
    },
    {
      "size_bytes": 2148896,
      "path": "/home/kei/class_a10_2f/a10_env/lib/python3.12/site-packages/erfa/ufunc.abi3.so"
    },
    {
      "size_bytes": 1848968,
      "path": "/home/kei/class_a10_2f/cobaya_packages/code/classy/build/hyperspherical.opp"
    },
    {
      "size_bytes": 1848960,
      "path": "/home/kei/class_a10_2f/packages/code/classy_old/build/hyperspherical.opp"
    },
    {
      "size_bytes": 1848912,
      "path": "/home/kei/class_a10_2f/build/hyperspherical.opp"
    },
    {
      "size_bytes": 1751528,
      "path": "/home/kei/class_a10_2f/a10_env/lib/python3.12/site-packages/astropy/stats/_stats.abi3.so"
    },
    {
      "size_bytes": 1664240,
      "path": "/home/kei/class_a10_2f/build/transfer.opp"
    },
    {
      "size_bytes": 1662176,
      "path": "/home/kei/class_a10_2f/packages/code/classy_old/build/transfer.opp"
    },
    {
      "size_bytes": 1662176,
      "path": "/home/kei/class_a10_2f/cobaya_packages/code/classy/build/transfer.opp"
    },
    {
      "size_bytes": 1569368,
      "path": "/home/kei/class_a10_2f/build/hmcode.opp"
    },
    {
      "size_bytes": 1567616,
      "path": "/home/kei/class_a10_2f/packages/code/classy_old/build/arrays.opp"
    },
    {
      "size_bytes": 1567616,
      "path": "/home/kei/class_a10_2f/cobaya_packages/code/classy/build/arrays.opp"
    },
    {
      "size_bytes": 1567560,
      "path": "/home/kei/class_a10_2f/build/arrays.opp"
    },
    {
      "size_bytes": 1567304,
      "path": "/home/kei/class_a10_2f/packages/code/classy_old/build/hmcode.opp"
    },
    {
      "size_bytes": 1567304,
      "path": "/home/kei/class_a10_2f/cobaya_packages/code/classy/build/hmcode.opp"
    },
    {
      "size_bytes": 1492880,
      "path": "/home/kei/class_a10_2f/build/primordial.opp"
    },
    {
      "size_bytes": 1492824,
      "path": "/home/kei/class_a10_2f/cobaya_packages/code/classy/build/primordial.opp"
    },
    {
      "size_bytes": 1492816,
      "path": "/home/kei/class_a10_2f/packages/code/classy_old/build/primordial.opp"
    },
    {
      "size_bytes": 1470640,
      "path": "/home/kei/class_a10_2f/a10_env/lib/python3.12/site-packages/astropy/timeseries/periodograms/lombscargle/implementations/cython_impl.abi3.so"
    },
    {
      "size_bytes": 1388664,
      "path": "/home/kei/class_a10_2f/build/harmonic.opp"
    }
  ],
  "keyword_categories": {
    "ua10_": {
      "count_preview": 168,
      "preview": [
        "/home/kei/class_a10_2f/unified_a10.yaml",
        "/home/kei/class_a10_2f/run_a10_h0_free.py",
        "/home/kei/class_a10_2f/check_73.py",
        "/home/kei/class_a10_2f/a10_debug.yaml",
        "/home/kei/class_a10_2f/a10_phase4_shoes.yaml",
        "/home/kei/class_a10_2f/a10_prod_run.2.txt.bak",
        "/home/kei/class_a10_2f/a10_wp0_valley.margestats",
        "/home/kei/class_a10_2f/a10_profile_68.yaml",
        "/home/kei/class_a10_2f/a10_bao_run.likestats",
        "/home/kei/class_a10_2f/a10_rescue.yaml",
        "/home/kei/class_a10_2f/a10_wp0_valley.covmat",
        "/home/kei/class_a10_2f/build/lib.linux-x86_64-cpython-312/classy/run_a10_h0_free.py",
        "/home/kei/class_a10_2f/build/lib.linux-x86_64-cpython-312/classy/check_73.py",
        "/home/kei/class_a10_2f/build/lib.linux-x86_64-cpython-312/classy/The_Final_Universe.py",
        "/home/kei/class_a10_2f/build/lib.linux-x86_64-cpython-312/classy/plot_hybrid_spectra.py",
        "/home/kei/class_a10_2f/build/lib.linux-x86_64-cpython-312/classy/cmb_validation_golden_model.py",
        "/home/kei/class_a10_2f/build/lib.linux-x86_64-cpython-312/classy/scan_residual.py",
        "/home/kei/class_a10_2f/build/lib.linux-x86_64-cpython-312/classy/run_ratio_test.py",
        "/home/kei/class_a10_2f/build/lib.linux-x86_64-cpython-312/classy/generate_a10_only.py",
        "/home/kei/class_a10_2f/build/lib.linux-x86_64-cpython-312/classy/final_audit.py",
        "/home/kei/class_a10_2f/build/lib.linux-x86_64-cpython-312/classy/my_old_classy_script.py",
        "/home/kei/class_a10_2f/build/lib.linux-x86_64-cpython-312/classy/step2_a10_ratio.py",
        "/home/kei/class_a10_2f/build/lib.linux-x86_64-cpython-312/classy/test_isolate.py",
        "/home/kei/class_a10_2f/build/lib.linux-x86_64-cpython-312/classy/include/background.h",
        "/home/kei/class_a10_2f/build/lib.linux-x86_64-cpython-312/classy/include/background.h.a10_bak",
        "/home/kei/class_a10_2f/build/lib.linux-x86_64-cpython-312/classy/test_hybrid_collision.py",
        "/home/kei/class_a10_2f/build/lib.linux-x86_64-cpython-312/classy/source/background.c",
        "/home/kei/class_a10_2f/build/lib.linux-x86_64-cpython-312/classy/source/input.c",
        "/home/kei/class_a10_2f/build/lib.linux-x86_64-cpython-312/classy/source/perturbations.c",
        "/home/kei/class_a10_2f/build/lib.linux-x86_64-cpython-312/classy/test_perturbations.py",
        "/home/kei/class_a10_2f/build/lib.linux-x86_64-cpython-312/classy/scan_jacobian.py",
        "/home/kei/class_a10_2f/build/lib.linux-x86_64-cpython-312/classy/verify_residual.py",
        "/home/kei/class_a10_2f/a10_profile_70.yaml",
        "/home/kei/class_a10_2f/chains/a10_run2.input.yaml",
        "/home/kei/class_a10_2f/chains/a10_phase4_shoes.covmat",
        "/home/kei/class_a10_2f/chains/a10_profile_71.minimize.updated.yaml",
        "/home/kei/class_a10_2f/chains/a10_wp0_valley.covmat",
        "/home/kei/class_a10_2f/chains/a10_profile_69.minimum.txt",
        "/home/kei/class_a10_2f/chains/a10_prod_run.3.txt",
        "/home/kei/class_a10_2f/chains/a10_phase4_shoes.1.txt"
      ]
    },
    "A10": {
      "count_preview": 124,
      "preview": [
        "/home/kei/class_a10_2f/unified_a10.yaml",
        "/home/kei/class_a10_2f/a10_2f_ef_safe.yaml",
        "/home/kei/class_a10_2f/run_a10_h0_free.py",
        "/home/kei/class_a10_2f/get_bestfit.py",
        "/home/kei/class_a10_2f/check_73.py",
        "/home/kei/class_a10_2f/run_a10_final.py",
        "/home/kei/class_a10_2f/build/lib.linux-x86_64-cpython-312/classy/run_a10_h0_free.py",
        "/home/kei/class_a10_2f/build/lib.linux-x86_64-cpython-312/classy/get_bestfit.py",
        "/home/kei/class_a10_2f/build/lib.linux-x86_64-cpython-312/classy/check_73.py",
        "/home/kei/class_a10_2f/build/lib.linux-x86_64-cpython-312/classy/run_a10_final.py",
        "/home/kei/class_a10_2f/build/lib.linux-x86_64-cpython-312/classy/fix_segfault_a10.py",
        "/home/kei/class_a10_2f/build/lib.linux-x86_64-cpython-312/classy/rescue_a10.py",
        "/home/kei/class_a10_2f/build/lib.linux-x86_64-cpython-312/classy/test_a10_final.py",
        "/home/kei/class_a10_2f/build/lib.linux-x86_64-cpython-312/classy/The_Final_Universe.py",
        "/home/kei/class_a10_2f/build/lib.linux-x86_64-cpython-312/classy/test_a10.py",
        "/home/kei/class_a10_2f/build/lib.linux-x86_64-cpython-312/classy/plot_hybrid_spectra.py",
        "/home/kei/class_a10_2f/build/lib.linux-x86_64-cpython-312/classy/run_a10_success.py",
        "/home/kei/class_a10_2f/build/lib.linux-x86_64-cpython-312/classy/scan_residual.py",
        "/home/kei/class_a10_2f/build/lib.linux-x86_64-cpython-312/classy/compare_cmb.py",
        "/home/kei/class_a10_2f/build/lib.linux-x86_64-cpython-312/classy/run_ratio_test.py",
        "/home/kei/class_a10_2f/build/lib.linux-x86_64-cpython-312/classy/generate_a10_only.py",
        "/home/kei/class_a10_2f/build/lib.linux-x86_64-cpython-312/classy/analyze_gate.py",
        "/home/kei/class_a10_2f/build/lib.linux-x86_64-cpython-312/classy/final_audit.py",
        "/home/kei/class_a10_2f/build/lib.linux-x86_64-cpython-312/classy/my_old_classy_script.py",
        "/home/kei/class_a10_2f/build/lib.linux-x86_64-cpython-312/classy/step2_a10_ratio.py",
        "/home/kei/class_a10_2f/build/lib.linux-x86_64-cpython-312/classy/test_isolate.py",
        "/home/kei/class_a10_2f/build/lib.linux-x86_64-cpython-312/classy/plot_a10.py",
        "/home/kei/class_a10_2f/build/lib.linux-x86_64-cpython-312/classy/auto_test_a10.py",
        "/home/kei/class_a10_2f/build/lib.linux-x86_64-cpython-312/classy/include/background.h",
        "/home/kei/class_a10_2f/build/lib.linux-x86_64-cpython-312/classy/include/background.h.a10_bak",
        "/home/kei/class_a10_2f/build/lib.linux-x86_64-cpython-312/classy/include/perturbations.h",
        "/home/kei/class_a10_2f/build/lib.linux-x86_64-cpython-312/classy/test_a10_evaluation.py",
        "/home/kei/class_a10_2f/build/lib.linux-x86_64-cpython-312/classy/plot_cmb.py",
        "/home/kei/class_a10_2f/build/lib.linux-x86_64-cpython-312/classy/debug_a10_point.py",
        "/home/kei/class_a10_2f/build/lib.linux-x86_64-cpython-312/classy/free_a10_parser.py",
        "/home/kei/class_a10_2f/build/lib.linux-x86_64-cpython-312/classy/test_hybrid_collision.py",
        "/home/kei/class_a10_2f/build/lib.linux-x86_64-cpython-312/classy/source/background.c",
        "/home/kei/class_a10_2f/build/lib.linux-x86_64-cpython-312/classy/source/input.c",
        "/home/kei/class_a10_2f/build/lib.linux-x86_64-cpython-312/classy/source/perturbations.c",
        "/home/kei/class_a10_2f/build/lib.linux-x86_64-cpython-312/classy/test_perturbations.py"
      ]
    },
    "repaired_unified": {
      "count_preview": 0,
      "preview": []
    },
    "phi_trigger": {
      "count_preview": 139,
      "preview": [
        "/home/kei/class_a10_2f/unified_a10.yaml",
        "/home/kei/class_a10_2f/run_a10_h0_free.py",
        "/home/kei/class_a10_2f/check_73.py",
        "/home/kei/class_a10_2f/a10_debug.yaml",
        "/home/kei/class_a10_2f/a10_phase4_shoes.yaml",
        "/home/kei/class_a10_2f/a10_wp0_valley.margestats",
        "/home/kei/class_a10_2f/a10_profile_68.yaml",
        "/home/kei/class_a10_2f/a10_rescue.yaml",
        "/home/kei/class_a10_2f/a10_wp0_valley.covmat",
        "/home/kei/class_a10_2f/build/lib.linux-x86_64-cpython-312/classy/run_a10_h0_free.py",
        "/home/kei/class_a10_2f/build/lib.linux-x86_64-cpython-312/classy/check_73.py",
        "/home/kei/class_a10_2f/build/lib.linux-x86_64-cpython-312/classy/The_Final_Universe.py",
        "/home/kei/class_a10_2f/build/lib.linux-x86_64-cpython-312/classy/plot_hybrid_spectra.py",
        "/home/kei/class_a10_2f/build/lib.linux-x86_64-cpython-312/classy/cmb_validation_golden_model.py",
        "/home/kei/class_a10_2f/build/lib.linux-x86_64-cpython-312/classy/scan_residual.py",
        "/home/kei/class_a10_2f/build/lib.linux-x86_64-cpython-312/classy/run_ratio_test.py",
        "/home/kei/class_a10_2f/build/lib.linux-x86_64-cpython-312/classy/generate_a10_only.py",
        "/home/kei/class_a10_2f/build/lib.linux-x86_64-cpython-312/classy/final_audit.py",
        "/home/kei/class_a10_2f/build/lib.linux-x86_64-cpython-312/classy/my_old_classy_script.py",
        "/home/kei/class_a10_2f/build/lib.linux-x86_64-cpython-312/classy/step2_a10_ratio.py",
        "/home/kei/class_a10_2f/build/lib.linux-x86_64-cpython-312/classy/test_isolate.py",
        "/home/kei/class_a10_2f/build/lib.linux-x86_64-cpython-312/classy/include/background.h",
        "/home/kei/class_a10_2f/build/lib.linux-x86_64-cpython-312/classy/include/background.h.a10_bak",
        "/home/kei/class_a10_2f/build/lib.linux-x86_64-cpython-312/classy/test_hybrid_collision.py",
        "/home/kei/class_a10_2f/build/lib.linux-x86_64-cpython-312/classy/source/background.c",
        "/home/kei/class_a10_2f/build/lib.linux-x86_64-cpython-312/classy/source/input.c",
        "/home/kei/class_a10_2f/build/lib.linux-x86_64-cpython-312/classy/test_perturbations.py",
        "/home/kei/class_a10_2f/build/lib.linux-x86_64-cpython-312/classy/scan_jacobian.py",
        "/home/kei/class_a10_2f/a10_profile_70.yaml",
        "/home/kei/class_a10_2f/chains/a10_run2.input.yaml",
        "/home/kei/class_a10_2f/chains/a10_phase4_shoes.covmat",
        "/home/kei/class_a10_2f/chains/a10_profile_71.minimize.updated.yaml",
        "/home/kei/class_a10_2f/chains/a10_wp0_valley.covmat",
        "/home/kei/class_a10_2f/chains/a10_profile_69.minimum.txt",
        "/home/kei/class_a10_2f/chains/a10_phase4_shoes.1.txt",
        "/home/kei/class_a10_2f/chains/a10_scout_H0_72.covmat",
        "/home/kei/class_a10_2f/chains/a10_main_rescue.1.txt",
        "/home/kei/class_a10_2f/chains/a10_main_rescue.covmat",
        "/home/kei/class_a10_2f/chains/a10_run2.updated.yaml",
        "/home/kei/class_a10_2f/chains/a10_profile_72.minimum"
      ]
    },
    "log10_ua10": {
      "count_preview": 0,
      "preview": []
    },
    "SH0ES": {
      "count_preview": 11,
      "preview": [
        "/home/kei/class_a10_2f/a10_phase4_shoes.yaml",
        "/home/kei/class_a10_2f/packages/data/sn_data/PantheonPlus/config.dataset",
        "/home/kei/class_a10_2f/packages/data/sn_data/PantheonPlus/Pantheon+SH0ES.dat",
        "/home/kei/class_a10_2f/packages/data/sn_data/README.md",
        "/home/kei/class_a10_2f/a10_env/lib64/python3.12/site-packages/cobaya/likelihoods/sn/pantheonplus.py",
        "/home/kei/class_a10_2f/a10_env/lib64/python3.12/site-packages/cobaya/likelihoods/sn/pantheonplusshoes.py",
        "/home/kei/class_a10_2f/a10_env/lib/python3.12/site-packages/cobaya/likelihoods/sn/pantheonplus.py",
        "/home/kei/class_a10_2f/a10_env/lib/python3.12/site-packages/cobaya/likelihoods/sn/pantheonplusshoes.py",
        "/home/kei/class_a10_2f/cobaya_packages/data/sn_data/PantheonPlus/config.dataset",
        "/home/kei/class_a10_2f/cobaya_packages/data/sn_data/PantheonPlus/Pantheon+SH0ES.dat",
        "/home/kei/class_a10_2f/cobaya_packages/data/sn_data/README.md"
      ]
    },
    "Pantheon": {
      "count_preview": 49,
      "preview": [
        "/home/kei/class_a10_2f/packages/data/sn_data/PantheonPlus/config.dataset",
        "/home/kei/class_a10_2f/packages/data/sn_data/Pantheon/full_long.dataset",
        "/home/kei/class_a10_2f/packages/data/sn_data/README.md",
        "/home/kei/class_a10_2f/chains/a10_profile_71.minimize.updated.yaml",
        "/home/kei/class_a10_2f/chains/a10_run2.updated.yaml",
        "/home/kei/class_a10_2f/chains/a10_profile_69.minimize.updated.yaml",
        "/home/kei/class_a10_2f/chains/a10_wp0_valley.updated.yaml",
        "/home/kei/class_a10_2f/chains/a10_profile_73.minimize.updated.yaml",
        "/home/kei/class_a10_2f/chains/a10_run1.updated.yaml",
        "/home/kei/class_a10_2f/chains/a10_phase4_shoes.updated.yaml",
        "/home/kei/class_a10_2f/chains/a10_scout_H0_72.updated.yaml",
        "/home/kei/class_a10_2f/chains/a10_profile_70.minimize.updated.yaml",
        "/home/kei/class_a10_2f/chains/a10_prod_run.updated.yaml",
        "/home/kei/class_a10_2f/chains/a10_main_rescue.updated.yaml",
        "/home/kei/class_a10_2f/chains/a10_profile_68.minimize.updated.yaml",
        "/home/kei/class_a10_2f/chains/a10_profile_72.minimize.updated.yaml",
        "/home/kei/class_a10_2f/a10_bao_run.updated.yaml",
        "/home/kei/class_a10_2f/a10_env/lib64/python3.12/site-packages/cobaya/cosmo_input/input_database.py",
        "/home/kei/class_a10_2f/a10_env/lib64/python3.12/site-packages/cobaya/likelihoods/base_classes/sn.py",
        "/home/kei/class_a10_2f/a10_env/lib64/python3.12/site-packages/cobaya/likelihoods/H0/riess2020Mb.yaml",
        "/home/kei/class_a10_2f/a10_env/lib64/python3.12/site-packages/cobaya/likelihoods/sn/pantheon.yaml",
        "/home/kei/class_a10_2f/a10_env/lib64/python3.12/site-packages/cobaya/likelihoods/sn/pantheon.py",
        "/home/kei/class_a10_2f/a10_env/lib64/python3.12/site-packages/cobaya/likelihoods/sn/pantheon.bibtex",
        "/home/kei/class_a10_2f/a10_env/lib64/python3.12/site-packages/cobaya/likelihoods/sn/union3.py",
        "/home/kei/class_a10_2f/a10_env/lib64/python3.12/site-packages/cobaya/likelihoods/sn/desdovekie.py",
        "/home/kei/class_a10_2f/a10_env/lib64/python3.12/site-packages/cobaya/likelihoods/sn/desy5.py",
        "/home/kei/class_a10_2f/a10_env/lib64/python3.12/site-packages/cobaya/likelihoods/sn/pantheonplus.py",
        "/home/kei/class_a10_2f/a10_env/lib64/python3.12/site-packages/cobaya/likelihoods/sn/pantheonplus.bibtex",
        "/home/kei/class_a10_2f/a10_env/lib64/python3.12/site-packages/cobaya/likelihoods/sn/pantheonplus.yaml",
        "/home/kei/class_a10_2f/a10_env/lib64/python3.12/site-packages/cobaya/likelihoods/sn/pantheonplusshoes.yaml",
        "/home/kei/class_a10_2f/a10_env/lib64/python3.12/site-packages/cobaya/likelihoods/sn/pantheonplusshoes.py",
        "/home/kei/class_a10_2f/a10_env/lib/python3.12/site-packages/cobaya/cosmo_input/input_database.py",
        "/home/kei/class_a10_2f/a10_env/lib/python3.12/site-packages/cobaya/likelihoods/base_classes/sn.py",
        "/home/kei/class_a10_2f/a10_env/lib/python3.12/site-packages/cobaya/likelihoods/H0/riess2020Mb.yaml",
        "/home/kei/class_a10_2f/a10_env/lib/python3.12/site-packages/cobaya/likelihoods/sn/pantheon.yaml",
        "/home/kei/class_a10_2f/a10_env/lib/python3.12/site-packages/cobaya/likelihoods/sn/pantheon.py",
        "/home/kei/class_a10_2f/a10_env/lib/python3.12/site-packages/cobaya/likelihoods/sn/pantheon.bibtex",
        "/home/kei/class_a10_2f/a10_env/lib/python3.12/site-packages/cobaya/likelihoods/sn/union3.py",
        "/home/kei/class_a10_2f/a10_env/lib/python3.12/site-packages/cobaya/likelihoods/sn/desdovekie.py",
        "/home/kei/class_a10_2f/a10_env/lib/python3.12/site-packages/cobaya/likelihoods/sn/desy5.py"
      ]
    },
    "plik": {
      "count_preview": 179,
      "preview": [
        "/home/kei/class_a10_2f/unified_a10.yaml",
        "/home/kei/class_a10_2f/a10_2f_ef_safe.yaml",
        "/home/kei/class_a10_2f/a10_debug.yaml",
        "/home/kei/class_a10_2f/a10_phase4_shoes.yaml",
        "/home/kei/class_a10_2f/a10_prod_run.2.txt.bak",
        "/home/kei/class_a10_2f/a10_wp0_valley.margestats",
        "/home/kei/class_a10_2f/a10_profile_68.yaml",
        "/home/kei/class_a10_2f/packages/data/planck_2018/baseline/plc_3.0/hi_l/plik_lite/plik_lite_v22_TTTEEE.clik/clik/lkl_0/_mdb",
        "/home/kei/class_a10_2f/packages/data/planck_2018/baseline/plc_3.0/hi_l/plik_lite/plik_lite_v22_TT.clik/clik/lkl_0/_mdb",
        "/home/kei/class_a10_2f/packages/data/planck_2018/baseline/plc_3.0/hi_l/plik/plik_recommended_priors.txt",
        "/home/kei/class_a10_2f/packages/data/planck_2018/baseline/plc_3.0/cosmomc/batch3/plik_rd12_HM_v22_TT.ini",
        "/home/kei/class_a10_2f/packages/data/planck_2018/baseline/plc_3.0/cosmomc/batch3/plik_rd12_HM_v22b_TTTEEE.ini",
        "/home/kei/class_a10_2f/packages/data/planck_2018/baseline/plc_3.0/cosmomc/batch3/plik_rd12_HM_v22_TE.ini",
        "/home/kei/class_a10_2f/packages/data/planck_2018/baseline/plc_3.0/cosmomc/batch3/plik_rd12_HM_v22_EE.ini",
        "/home/kei/class_a10_2f/packages/data/planck_2018/baseline/readme_baseline.md",
        "/home/kei/class_a10_2f/packages/code/planck/clipy/clipy/__init__.py",
        "/home/kei/class_a10_2f/packages/code/planck/clipy/clipy/cmbonly.py",
        "/home/kei/class_a10_2f/packages/code/planck/clipy/clipy/lkl.py",
        "/home/kei/class_a10_2f/packages/code/planck/clipy/changelog.md",
        "/home/kei/class_a10_2f/packages/code/planck/clipy/README.md",
        "/home/kei/class_a10_2f/packages/code/classy_old/base_2015_plikHM_TT_lowTEB_lensing.ini",
        "/home/kei/class_a10_2f/packages/code/classy_old/build/lib.linux-x86_64-cpython-312/classy/source/input.c",
        "/home/kei/class_a10_2f/packages/code/classy_old/base_2018_plikHM_TTTEEE_lowl_lowE_lensing.ini",
        "/home/kei/class_a10_2f/packages/code/classy_old/source/input.c",
        "/home/kei/class_a10_2f/a10_bao_run.likestats",
        "/home/kei/class_a10_2f/a10_rescue.yaml",
        "/home/kei/class_a10_2f/base_2015_plikHM_TT_lowTEB_lensing.ini",
        "/home/kei/class_a10_2f/build/lib.linux-x86_64-cpython-312/classy/plot_a10.py",
        "/home/kei/class_a10_2f/build/lib.linux-x86_64-cpython-312/classy/source/input.c",
        "/home/kei/class_a10_2f/a10_profile_70.yaml",
        "/home/kei/class_a10_2f/chains/a10_run2.input.yaml",
        "/home/kei/class_a10_2f/chains/a10_profile_71.minimize.updated.yaml",
        "/home/kei/class_a10_2f/chains/a10_profile_69.minimum.txt",
        "/home/kei/class_a10_2f/chains/a10_prod_run.3.txt",
        "/home/kei/class_a10_2f/chains/a10_phase4_shoes.1.txt",
        "/home/kei/class_a10_2f/chains/a10_main_rescue.1.txt",
        "/home/kei/class_a10_2f/chains/a10_prod_run.5.txt",
        "/home/kei/class_a10_2f/chains/a10_run2.updated.yaml",
        "/home/kei/class_a10_2f/chains/a10_profile_72.minimum",
        "/home/kei/class_a10_2f/chains/a10_profile_68.minimum"
      ]
    },
    "BAO": {
      "count_preview": 200,
      "preview": [
        "/home/kei/class_a10_2f/unified_a10.yaml",
        "/home/kei/class_a10_2f/check_73.py",
        "/home/kei/class_a10_2f/a10_prod_run.2.txt.bak",
        "/home/kei/class_a10_2f/a10_wp0_valley.margestats",
        "/home/kei/class_a10_2f/packages/data/bao_data/README.md",
        "/home/kei/class_a10_2f/packages/code/classy_old/build/lib.linux-x86_64-cpython-312/classy/python/classy.pyx",
        "/home/kei/class_a10_2f/packages/code/classy_old/build/lib.linux-x86_64-cpython-312/classy/external/heating/noninjection.c",
        "/home/kei/class_a10_2f/packages/code/classy_old/build/lib.linux-x86_64-cpython-312/classy/include/precisions.h",
        "/home/kei/class_a10_2f/packages/code/classy_old/build/lib.linux-x86_64-cpython-312/classy/source/thermodynamics.c",
        "/home/kei/class_a10_2f/packages/code/classy_old/cpp/ClassEngine.hh",
        "/home/kei/class_a10_2f/packages/code/classy_old/python/classy.cpp",
        "/home/kei/class_a10_2f/packages/code/classy_old/python/classy.pyx",
        "/home/kei/class_a10_2f/packages/code/classy_old/scripts/cl_ST.py",
        "/home/kei/class_a10_2f/packages/code/classy_old/scripts/warmup.py",
        "/home/kei/class_a10_2f/packages/code/classy_old/scripts/varying_pann.py",
        "/home/kei/class_a10_2f/packages/code/classy_old/scripts/one_k.py",
        "/home/kei/class_a10_2f/packages/code/classy_old/scripts/varying_neff.py",
        "/home/kei/class_a10_2f/packages/code/classy_old/scripts/many_times.py",
        "/home/kei/class_a10_2f/packages/code/classy_old/scripts/one_time.py",
        "/home/kei/class_a10_2f/packages/code/classy_old/scripts/cltt_terms.py",
        "/home/kei/class_a10_2f/packages/code/classy_old/doc/input/chap2.md",
        "/home/kei/class_a10_2f/packages/code/classy_old/external/heating/noninjection.c",
        "/home/kei/class_a10_2f/packages/code/classy_old/include/precisions.h",
        "/home/kei/class_a10_2f/packages/code/classy_old/notebooks/one_time.ipynb",
        "/home/kei/class_a10_2f/packages/code/classy_old/notebooks/one_k.ipynb",
        "/home/kei/class_a10_2f/packages/code/classy_old/notebooks/warmup.ipynb",
        "/home/kei/class_a10_2f/packages/code/classy_old/notebooks/cl_ST.ipynb",
        "/home/kei/class_a10_2f/packages/code/classy_old/notebooks/cltt_terms.ipynb",
        "/home/kei/class_a10_2f/packages/code/classy_old/notebooks/varying_neff.ipynb",
        "/home/kei/class_a10_2f/packages/code/classy_old/notebooks/many_times.ipynb",
        "/home/kei/class_a10_2f/packages/code/classy_old/notebooks/varying_pann.ipynb",
        "/home/kei/class_a10_2f/packages/code/classy_old/source/thermodynamics.c",
        "/home/kei/class_a10_2f/a10_bao_run.likestats",
        "/home/kei/class_a10_2f/build/lib.linux-x86_64-cpython-312/classy/check_73.py",
        "/home/kei/class_a10_2f/build/lib.linux-x86_64-cpython-312/classy/python/classy.cpp",
        "/home/kei/class_a10_2f/build/lib.linux-x86_64-cpython-312/classy/python/classy.pyx",
        "/home/kei/class_a10_2f/build/lib.linux-x86_64-cpython-312/classy/external/heating/noninjection.c",
        "/home/kei/class_a10_2f/build/lib.linux-x86_64-cpython-312/classy/include/precisions.h",
        "/home/kei/class_a10_2f/build/lib.linux-x86_64-cpython-312/classy/source/thermodynamics.c",
        "/home/kei/class_a10_2f/chains/a10_run1.1.txt"
      ]
    }
  },
  "interpretation": "class_a10_2f is an A10 cosmology/CLASS working tree that should be preserved as a legacy branch snapshot. It is smaller than class_unified_a10 and class_hybrid_a10 but may contain two-field or intermediate A10 branch materials. Preserve compact snapshot; do not commit full 2.6G tree.",
  "cleanup_status": "snapshot_protected; original full folder can be moved to legacy_frozen. Do not delete until class_unified/class_hybrid provenance has been accepted and no unique outputs are needed."
}
